cjy_wfy7/__init__.py
cjy_wfy7/background.jpg
cjy_wfy7/crash.wav
cjy_wfy7/font.ttf
cjy_wfy7/kaiti.ttf
cjy_wfy7/main.py
cjy_wfy7/racecar.jpg
cjy_wfy7/racestart.wav
cjy_wfy7/tiantiande.wav
cjy_wfy7/photos/1.jpg
cjy_wfy7/photos/10.jpg
cjy_wfy7/photos/11.jpg
cjy_wfy7/photos/12.jpg
cjy_wfy7/photos/13.jpg
cjy_wfy7/photos/14.jpg
cjy_wfy7/photos/15.jpg
cjy_wfy7/photos/2.jpg
cjy_wfy7/photos/3.jpg
cjy_wfy7/photos/4.jpg
cjy_wfy7/photos/5.jpg
cjy_wfy7/photos/6.jpg
cjy_wfy7/photos/7.jpg
cjy_wfy7/photos/70.jpg
cjy_wfy7/photos/8.jpg
cjy_wfy7/photos/9.jpg
cjy_wfy7-0.0.1.dist-info/LICENSE
cjy_wfy7-0.0.1.dist-info/METADATA
cjy_wfy7-0.0.1.dist-info/WHEEL
cjy_wfy7-0.0.1.dist-info/top_level.txt
cjy_wfy7-0.0.1.dist-info/RECORD
